README.md
pyproject.toml
trustgraph/mcp_version.py
trustgraph/mcp_server/__init__.py
trustgraph/mcp_server/__main__.py
trustgraph/mcp_server/mcp.py
trustgraph/mcp_server/tg_socket.py
trustgraph_mcp.egg-info/PKG-INFO
trustgraph_mcp.egg-info/SOURCES.txt
trustgraph_mcp.egg-info/dependency_links.txt
trustgraph_mcp.egg-info/entry_points.txt
trustgraph_mcp.egg-info/requires.txt
trustgraph_mcp.egg-info/top_level.txt